lmoran_pack/__init__.py
lmoran_pack/lmoran_pack.py
lmoran_pack-0.1.2.dist-info/METADATA
lmoran_pack-0.1.2.dist-info/WHEEL
lmoran_pack-0.1.2.dist-info/top_level.txt
lmoran_pack-0.1.2.dist-info/RECORD
