Metadata-Version: 2.4
Name: lmoran_pack
Version: 0.1.2
Summary: Is a luh package yer
Author: Loic Moran
Author-email: lmoran@student.42.fr
Classifier: Programming Language :: Python :: 3
Classifier: License :: OSI Approved :: MIT License
Classifier: Operating System :: OS Independent
Requires-Python: >=3.6
Dynamic: author
Dynamic: author-email
Dynamic: classifier
Dynamic: requires-python
Dynamic: summary
